mycroft_bus_client/__init__.py
mycroft_bus_client/conf.py
mycroft_bus_client/message.py
mycroft_bus_client/send_func.py
mycroft_bus_client/client/__init__.py
mycroft_bus_client/client/client.py
mycroft_bus_client/client/collector.py
mycroft_bus_client/client/waiter.py
mycroft_bus_client/util/__init__.py
mycroft_bus_client/util/scheduler.py
mycroft_bus_client/util/utils.py
mycroft_messagebus_client-0.10.1.dist-info/LICENSE.md
mycroft_messagebus_client-0.10.1.dist-info/METADATA
mycroft_messagebus_client-0.10.1.dist-info/WHEEL
mycroft_messagebus_client-0.10.1.dist-info/top_level.txt
mycroft_messagebus_client-0.10.1.dist-info/RECORD
